itk/itkLabelSetErodeImageFilterPython.py
itk/itkLabelSetDilateImageFilterPython.py
itk/_LabelErodeDilatePython.cpython-39-aarch64-linux-gnu.so
itk/LabelErodeDilatePython.py
itk/itkLabelSetMorphBaseImageFilterPython.py
itk/Configuration/LabelErodeDilateConfig.py
itk/Configuration/LabelErodeDilate_snake_case.py
itk_labelerodedilate-1.3.3.dist-info/METADATA
itk_labelerodedilate-1.3.3.dist-info/RECORD
itk_labelerodedilate-1.3.3.dist-info/WHEEL
itk_labelerodedilate-1.3.3.dist-info/licenses/LICENSE
itk_labelerodedilate.libs/libtbb-e046f41a.so.12.9
