Metadata-Version: 2.1
Name: itk-labelerodedilate
Version: 1.3.3
Summary: An ITK module for erode and dilate operations on label images
Keywords: itk,InsightToolkit,Math-morphology,Label-images
Author-Email: Richard Beare <Richard.Beare@med.monash.edu.au>
License: 
Classifier: Development Status :: 4 - Beta
Classifier: Intended Audience :: Developers
Classifier: Intended Audience :: Education
Classifier: Intended Audience :: Healthcare Industry
Classifier: Intended Audience :: Science/Research
Classifier: License :: OSI Approved :: Apache Software License
Classifier: Operating System :: Android
Classifier: Operating System :: MacOS
Classifier: Operating System :: Microsoft :: Windows
Classifier: Operating System :: POSIX
Classifier: Operating System :: Unix
Classifier: Programming Language :: C++
Classifier: Programming Language :: Python
Classifier: Topic :: Scientific/Engineering
Classifier: Topic :: Scientific/Engineering :: Information Analysis
Classifier: Topic :: Scientific/Engineering :: Medical Science Apps.
Classifier: Topic :: Software Development :: Libraries
Project-URL: Download, https://github.com/InsightSoftwareConsortium/ITKLabelErodeDilate
Project-URL: Homepage, https://github.com/InsightSoftwareConsortium/ITKLabelErodeDilate
Requires-Python: >=3.9
Requires-Dist: itk==5.4.*
